{
    "version": 1.101,
    "util": {
        "1": {
            "type": "Download",
            "status": "Working ✔",
            "title": "Kieron Virus",
            "description": "This is a Simple script that i made that will change every image in every website to a Brain Rot on (Visit the Info Section and follow the tutorial on how to install it",
            "link": "https://guinea1980-svg.github.io/ZYME/Kieron%20Virus%20.UserScript.js"
        },
        "2": {
            "type": "Link",
            "status": "Working ✔",
            "title": "Tamper Monkey",
            "description": "This is a Chrome Extention that will run JS (Java Script) Code on Specific Websites its Great for Running Scripts on a website without opening the Console",
            "link": "https://chromewebstore.google.com/detail/tampermonkey/dhdgffkkebhmkfjojejmpbldmpobfkfo"
        },
        "3": {
            "type": "Link",
            "status": "Not Working ❌",
            "title": "SenAI",
            "description": "SenAi is a Website that Gives you the answers to questions in Seneca ",
            "link": "https://senai.uk/seneca"
        },
        "4": {
            "type": "Link",
            "status": "Working ✔",
            "title": "School Cheats",
            "description": "School Cheats is a Website with a whole load of cheating related stuff from a bot that plays that kahoot for you or Flooding and Crashing blooket lobbies. in short this Site is all around good for cheating in blooket or any related websites",
            "link": "https://senai.uk/seneca"
        },
        "5": {
            "type": "Link",
            "status": "Lorem ipsum dolor",
            "title": "Lorem ipsum dolor",
            "description": "Lorem ipsum dolor",
            "link": ""
        }
        
    },
    "prox": {
      "1": {
            "type": "Link",
            "status": "Working ✔",
            "title": "Interstellar",
            "description": "This is One of the Best Proxies Out Right Now that isnt Blocked (This is Updated Everytime this Proxy is blocked!!)",
            "link": "https://iamsteve.raspberryip.com/"
        }
    }
}
